mobilkit/__init__.py
mobilkit/dask_schemas.py
mobilkit/displacement.py
mobilkit/loader.py
mobilkit/spatial.py
mobilkit/stats.py
mobilkit/temporal.py
mobilkit/tools.py
mobilkit/viz.py
mobilkit-0.2.8.dist-info/LICENSE
mobilkit-0.2.8.dist-info/METADATA
mobilkit-0.2.8.dist-info/WHEEL
mobilkit-0.2.8.dist-info/top_level.txt
mobilkit-0.2.8.dist-info/RECORD
