Metadata-Version: 2.1
Name: mobilkit
Version: 0.2.8
Summary: A Python Toolkit for Urban Resilience and Disaster Risk Management Analytics using High Frequency Human Mobility Data
Home-page: https://github.com/mindearth/mobilkit
Author: MindEarth
Author-email: enrico.ubaldi@mindearth.org
Project-URL: Bug Tracker, https://github.com/mindearth/mobilkit/issues
Classifier: Programming Language :: Python :: 3
Classifier: License :: OSI Approved :: MIT License
Classifier: Intended Audience :: Science/Research
Classifier: Intended Audience :: Developers
Classifier: Topic :: Software Development
Classifier: Topic :: Scientific/Engineering
Classifier: Operating System :: Microsoft :: Windows
Classifier: Operating System :: Unix
Classifier: Operating System :: MacOS
Classifier: Programming Language :: Python :: 3.6
Classifier: Programming Language :: Python :: 3.7
Classifier: Programming Language :: Python :: 3.8
Classifier: Programming Language :: Python :: 3.9
Requires-Python: >=3.6
License-File: LICENSE
Requires-Dist: distributed[full] ==2023.5.0
Requires-Dist: dask[full] ==2023.5.0
Requires-Dist: click
Requires-Dist: geopandas
Requires-Dist: descartes
Requires-Dist: rtree
Requires-Dist: Fiona
Requires-Dist: geojson
Requires-Dist: haversine
Requires-Dist: joblib
Requires-Dist: matplotlib
Requires-Dist: pyarrow
Requires-Dist: scikit-learn
Requires-Dist: scipy
Requires-Dist: seaborn
Requires-Dist: statsmodels
Requires-Dist: requests
Provides-Extra: complete
Requires-Dist: ipykernel ; extra == 'complete'
Requires-Dist: ipython ; extra == 'complete'
Requires-Dist: ipython-genutils ; extra == 'complete'
Requires-Dist: jupyter ; extra == 'complete'
Requires-Dist: notebook ; extra == 'complete'
Requires-Dist: sphinx ; extra == 'complete'
Requires-Dist: sphinx-rtd-theme ; extra == 'complete'
Requires-Dist: docutils ; extra == 'complete'
Requires-Dist: nbsphinx ; extra == 'complete'
Requires-Dist: jinja2 ; extra == 'complete'
Requires-Dist: contextily ; extra == 'complete'
Requires-Dist: scikit-mobility ; extra == 'complete'
Requires-Dist: pandas ==1.2.5 ; extra == 'complete'
Requires-Dist: geopandas <0.11.0,>=0.10.2 ; extra == 'complete'
Requires-Dist: infostop ; extra == 'complete'
Provides-Extra: doc
Requires-Dist: ipykernel ; extra == 'doc'
Requires-Dist: ipython ; extra == 'doc'
Requires-Dist: ipython-genutils ; extra == 'doc'
Requires-Dist: jupyter ; extra == 'doc'
Requires-Dist: notebook ; extra == 'doc'
Requires-Dist: sphinx ; extra == 'doc'
Requires-Dist: sphinx-rtd-theme ; extra == 'doc'
Requires-Dist: docutils ; extra == 'doc'
Requires-Dist: nbsphinx ; extra == 'doc'
Requires-Dist: jinja2 ; extra == 'doc'
Provides-Extra: locations
Requires-Dist: infostop ; extra == 'locations'
Provides-Extra: skmob
Requires-Dist: scikit-mobility ; extra == 'skmob'
Requires-Dist: pandas ==1.2.5 ; extra == 'skmob'
Requires-Dist: geopandas <0.11.0,>=0.10.2 ; extra == 'skmob'
Provides-Extra: viz
Requires-Dist: contextily ; extra == 'viz'
